setup.py
ttanupri_distributions/Binomialdistribution.py
ttanupri_distributions/Gaussiandistribution.py
ttanupri_distributions/Generaldistribution.py
ttanupri_distributions/__init__.py
ttanupri_distributions.egg-info/PKG-INFO
ttanupri_distributions.egg-info/SOURCES.txt
ttanupri_distributions.egg-info/dependency_links.txt
ttanupri_distributions.egg-info/not-zip-safe
ttanupri_distributions.egg-info/top_level.txt